verilogHW1.v
module memtomemtrans(clock,reset,dataina);

/*Input Ports*/
input reset,clock;
input [7:0] dataina;

/*Unidirectional, SRAM like memory declaration*/
reg [7:0] mema [7:0];
reg [7:0] memb [4:0];

reg [4:0] temp;
reg wea,incb,web;
reg rstinput,inca;
reg [2:0] addra;
reg [1:0] addrb;
reg [7:0] dout1;
reg [7:0] dout2;
reg [7:0] result;
reg [7:0] addout;
reg [7:0] subout;
reg [7:0] datainb;

initial 
begin 
addra =-1;
addrb = 0;
temp = 0;
wea = 0;
web = 0;
inca = 0;
incb = 0;
datainb = 0;
end

always @(posedge clock)
begin
 if(rstinput==1) 
 begin
 temp = 5'b0000;
 end 
 else 
 begin   
temp = temp + 1; /*Increment the 5-bit counter for the controller*/
/*Reduced expressions for counter-decoder scheme*/ 
wea = (~temp[4]&~temp[3]&temp[2]) | (~temp[4]&~temp[3]&temp[1]) | (~temp[4]&~temp[3]&~temp[2]&temp[0]) | (temp[3]&~temp[1]&~temp[0]&~temp[4]&~temp[2]);
incb = (~temp[4]&temp[3]&temp[2]&temp[0]) | (~temp[4]&temp[3]&temp[1]&temp[0]);
inca = 1;
/*web = (~temp[4]&temp[3]&~temp[2]&temp[1]&~temp[0]) | (~temp[4]&temp[3]&temp[2]&~temp[1]&~temp[0]) | (~temp[4]&temp[3]&temp[2]&temp[1]&~temp[0]) 
| (temp[4]&~temp[3]&~temp[2]&~temp[1]&~temp[0]);*/
web = (~temp[4] & temp[3] & temp[2] & ~temp[0]) | (~temp[4] & temp[3] & temp[1] & ~temp[0]) | (temp[4] & ~temp[3] & ~temp[2] & ~temp[1] & ~temp[0]);
rstinput = (temp[4]&~temp[3]&~temp[2]&temp[1]&~temp[0]) | reset; /*Reset after 18 clock cycles*/
end

/*Counters to determine the addresses for Memory A and B*/
if(reset)
begin
addra <= 0;
addrb <= 0;
end
else
begin
if(inca)
addra <= addra + 1;
if(incb)
addrb <= addrb + 1;
end

/*If write enable is set, write to memory; otherwise read from memory*/
if(wea) 
mema[addra] <= dataina;

if(wea==0) 
begin
dout1 <= mema[addra];
dout2 <= dout1;
end
end

/*Calculate add & sub result*/
always @(dout2 or dout1)
begin
addout <= dout2 + dout1;
subout <= dout2 - dout1;
result <= dout1 - dout2;
end

/*Depending on M.S.B, write the result to Memory B*/
always @(result[7] or addout or subout)
begin 
if(web)
begin
if(result[7]) datainb = addout;
else 		  datainb = subout;	
memb[addrb] <= datainb;
end	
end
endmodule

verilogHW1test.v
`include "verilogHW1.v"
`timescale 10s/1s

module memtomemtranstest;
reg reset_tb,clock_tb;
reg [7:0] dataina_tb;

reg [7:0] memB0;
reg [7:0] memB1;
reg [7:0] memB2;	
reg [7:0] memB3;

memtomemtrans i1 (.reset(reset_tb),.clock(clock_tb),.dataina(dataina_tb));

initial
begin
$dumpfile("memtomemtrans.vcd");
$dumpvars(0,memtomemtranstest);
clock_tb = 0; reset_tb = 0;
#1  dataina_tb = 4;
#2  dataina_tb = 2;
#2  dataina_tb = 8;
#2  dataina_tb = 19;
#2  dataina_tb = 31;
#2  dataina_tb = 29;
#2  dataina_tb = 22;
#2  dataina_tb = 30;
end
always #1 clock_tb = ~clock_tb;
always #34 reset_tb = 1;

always @(posedge clock_tb)
begin
memB0 <= i1.memb[0];
memB1 <= i1.memb[1];
memB2 <= i1.memb[2];
memB3 <= i1.memb[3];
end
endmodule

memtomemtrans.vcd
$date
	Thu Sep 29 00:18:21 2016
$end
$version
	Icarus Verilog
$end
$timescale
	1s
$end
$scope module memtomemtranstest $end
$var reg 1 ! clock_tb $end
$var reg 8 " dataina_tb [7:0] $end
$var reg 8 # memB0 [7:0] $end
$var reg 8 $ memB1 [7:0] $end
$var reg 8 % memB2 [7:0] $end
$var reg 8 & memB3 [7:0] $end
$var reg 1 ' reset_tb $end
$scope module i1 $end
$var wire 1 ( clock $end
$var wire 8 ) dataina [7:0] $end
$var wire 1 * reset $end
$var reg 8 + addout [7:0] $end
$var reg 3 , addra [2:0] $end
$var reg 2 - addrb [1:0] $end
$var reg 8 . datainb [7:0] $end
$var reg 8 / dout1 [7:0] $end
$var reg 8 0 dout2 [7:0] $end
$var reg 1 1 inca $end
$var reg 1 2 incb $end
$var reg 8 3 result [7:0] $end
$var reg 1 4 rstinput $end
$var reg 8 5 subout [7:0] $end
$var reg 5 6 temp [4:0] $end
$var reg 1 7 wea $end
$var reg 1 8 web $end
$upscope $end
$upscope $end
$enddefinitions $end
#0
$dumpvars
08
07
b0 6
bx 5
x4
bx 3
02
01
bx 0
bx /
b0 .
b0 -
b111 ,
bx +
0*
bx )
0(
0'
bx &
bx %
bx $
bx #
bx "
0!
$end
#10
b0 ,
04
11
17
b1 6
1!
1(
b100 "
b100 )
#20
0!
0(
#30
b1 ,
b10 6
1!
1(
b10 "
b10 )
#40
0!
0(
#50
b10 ,
b11 6
1!
1(
b1000 "
b1000 )
#60
0!
0(
#70
b11 ,
b100 6
1!
1(
b10011 "
b10011 )
#80
0!
0(
#90
b100 ,
b101 6
1!
1(
b11111 "
b11111 )
#100
0!
0(
#110
b101 ,
b110 6
1!
1(
b11101 "
b11101 )
#120
0!
0(
#130
b110 ,
b111 6
1!
1(
b10110 "
b10110 )
#140
0!
0(
#150
b111 ,
b1000 6
1!
1(
b11110 "
b11110 )
#160
0!
0(
#170
b100 /
b0 ,
07
b1001 6
1!
1(
#180
0!
0(
#190
b110 .
b11111110 3
b10 5
b110 +
b100 0
b10 /
b1 ,
18
b1010 6
1!
1(
#200
0!
0(
#210
b110 3
b11111010 5
b1010 +
b10 0
b1000 /
b1 -
b10 ,
b110 #
08
12
b1011 6
1!
1(
#220
0!
0(
#230
b11110101 .
b1011 3
b11110101 5
b11011 +
b1000 0
b10011 /
b11 ,
18
02
b1100 6
1!
1(
#240
0!
0(
#250
b1100 3
b11110100 5
b110010 +
b10011 0
b11111 /
b10 -
b100 ,
b11110101 $
08
12
b1101 6
1!
1(
#260
0!
0(
#270
b111100 .
b11111110 3
b10 5
b111100 +
b11111 0
b11101 /
b101 ,
18
02
b1110 6
1!
1(
#280
0!
0(
#290
b11111001 3
b111 5
b110011 +
b11101 0
b10110 /
b11 -
b110 ,
b111100 %
08
12
b1111 6
1!
1(
#300
0!
0(
#310
b11111000 .
b1000 3
b11111000 5
b110100 +
b10110 0
b11110 /
b111 ,
18
02
b10000 6
1!
1(
#320
0!
0(
#330
b11100110 3
b11010 5
b100010 +
b11110 0
b100 /
b0 ,
b11111000 &
08
b10001 6
1!
1(
#340
0!
0(
1'
1*
#350
b11111110 3
b10 5
b110 +
b100 0
b10 /
b0 -
14
b10010 6
1!
1(
#360
0!
0(
#370
b0 3
b0 5
b100 +
b10 0
b0 6
1!
1(
